buttplug/__init__.py
buttplug/client/__init__.py
buttplug/client/client.py
buttplug/connectors/__init__.py
buttplug/connectors/abstract.py
buttplug/connectors/websocket.py
buttplug/errors/__init__.py
buttplug/errors/base.py
buttplug/errors/client.py
buttplug/errors/server.py
buttplug/messages/__init__.py
buttplug/messages/machinery.py
buttplug/messages/v0.py
buttplug/messages/v1.py
buttplug/messages/v2.py
buttplug/messages/v3.py
buttplug/utils/__init__.py
buttplug/utils/cases.py
buttplug/utils/dict.py
buttplug_py-0.2.0.dist-info/LICENSE
buttplug_py-0.2.0.dist-info/METADATA
buttplug_py-0.2.0.dist-info/WHEEL
buttplug_py-0.2.0.dist-info/top_level.txt
buttplug_py-0.2.0.dist-info/RECORD
