Metadata-Version: 2.1
Name: buttplug-py
Version: 0.2.0
Summary: Python client implementation of the Buttplug Intimate Hardware Control Protocol.
Author-email: Siege Wizard <wizard.siege@gmail.com>
License: Buttplug-py is covered under the following BSD 3-Clause License
Project-URL: Homepage, https://github.com/siege-wizard/buttplug-py
Project-URL: Bug Tracker, https://github.com/siege-wizard/buttplug-py/issues
Classifier: Programming Language :: Python :: 3
Classifier: Development Status :: 4 - Beta
Classifier: License :: OSI Approved :: BSD License
Classifier: Operating System :: OS Independent
Requires-Python: >=3.9
License-File: LICENSE
Requires-Dist: websockets (>=10.4)
